<?xml version="1.0"?>
<GeneratorDefitions>

<!-- <gen class="AUI Events" type="interface">
  <gen class="AUI Events" type="interface">
    <event name="wxEVT_AUI_PANE_BUTTON" class="wxAuiManagerEvent" help=""/>
    <event name="wxEVT_AUI_PANE_CLOSE" class="wxAuiManagerEvent" help=""/>
    <event name="wxEVT_AUI_PANE_MAXIMIZE" class="wxAuiManagerEvent" help=""/>
    <event name="wxEVT_AUI_PANE_RESTORE" class="wxAuiManagerEvent" help=""/>
    <event name="wxEVT_AUI_PANE_ACTIVATED" class="wxAuiManagerEvent" help=""/>
    <event name="wxEVT_AUI_RENDER" class="wxAuiManagerEvent" help=""/>
    <event name="wxEVT_AUI_FIND_MANAGER" class="wxAuiManagerEvent" help=""/>
  </gen>

  <gen class="wxAuiNotebook" image="auinotebook" type="auinotebook">
    <inherits class="wxWindow"/>
    <inherits class="Window Events"/>
    <property name="var_name" type="string">m_auinotebook</property>
    <property name="class_access" type="option">
      <option name="none"/>
      <option name="protected:"/>
      <option name="public:"/>
      protected:
    </property>
    <property name="tab_ctrl_height" type="int"
        help="Sets the tab height. By default, the tab control height is calculated by measuring the text height and bitmap sizes on the tab captions. Calling this method will override that calculation and set the tab control to the specified height parameter. A call to this method will override any call to SetUniformBitmapSize(). Specifying -1 as the height will return the control to its default auto-sizing behaviour.">
      -1
    </property>
    <property name="uniform_bitmap_size" type="wxSize"
        help="SetUniformBitmapSize() ensures that all tabs will have the same height, even if some tabs don't have bitmaps. Passing wxDefaultSize to this function will instruct the control to use dynamic tab height, which is the default behaviour. Under the default behaviour, when a tab with a large bitmap is added, the tab control's height will automatically increase to accommodate the larger bitmap."/>
    <property name="style" type="bitlist">
      <option name="wxAUI_NB_DEFAULT_STYLE"
        help="Defined as wxAUI_NB_TOP | wxAUI_NB_TAB_SPLIT | wxAUI_NB_TAB_MOVE | wxAUI_NB_SCROLL_BUTTONS | wxAUI_NB_CLOSE_ON_ACTIVE_TAB | wxAUI_NB_MIDDLE_CLICK_CLOSE."/>
      <option name="wxAUI_NB_TAB_SPLIT" help="Allows the tab control to be split by dragging a tab."/>
      <option name="wxAUI_NB_TAB_MOVE" help="Allows a tab to be moved horizontally by dragging."/>
      <option name="wxAUI_NB_TAB_EXTERNAL_MOVE" help="Allows a tab to be moved to another tab control."/>
      <option name="wxAUI_NB_TAB_FIXED_WIDTH" help="With this style, all tabs have the same width."/>
      <option name="wxAUI_NB_SCROLL_BUTTONS" help="With this style, left and right scroll buttons are displayed."/>
      <option name="wxAUI_NB_WINDOWLIST_BUTTON" help="With this style, a drop-down list of windows is available."/>
      <option name="wxAUI_NB_CLOSE_BUTTON" help="With this style, a close button is available on the tab bar."/>
      <option name="wxAUI_NB_CLOSE_ON_ACTIVE_TAB" help="With this style, the close button is visible on the active tab."/>
      <option name="wxAUI_NB_CLOSE_ON_ALL_TABS" help="With this style, the close button is visible on all tabs."/>
      <option name="wxAUI_NB_MIDDLE_CLICK_CLOSE" help="With this style, middle click on a tab closes the tab."/>
      <option name="wxAUI_NB_TOP" help="With this style, tabs are drawn along the top of the notebook."/>
      <option name="wxAUI_NB_BOTTOM" help="With this style, tabs are drawn along the bottom of the notebook."/>
      wxAUI_NB_DEFAULT_STYLE
    </property>
    <event name="wxEVT_AUINOTEBOOK_PAGE_CLOSE" class="wxAuiNotebookEvent" help="A page is about to be closed."/>
    <event name="wxEVT_AUINOTEBOOK_PAGE_CLOSED" class="wxAuiNotebookEvent" help="A page has been closed."/>
    <event name="wxEVT_AUINOTEBOOK_PAGE_CHANGED" class="wxAuiNotebookEvent" help="The page selection was changed."/>
    <event name="wxEVT_AUINOTEBOOK_PAGE_CHANGING" class="wxAuiNotebookEvent"
        help="The page selection is about to be changed. This event can be vetoed."/>
    <event name="wxEVT_AUINOTEBOOK_BUTTON" class="wxAuiNotebookEvent" help="The window list button has been pressed."/>
    <event name="wxEVT_AUINOTEBOOK_BEGIN_DRAG" class="wxAuiNotebookEvent" help="Dragging is about to begin."/>
    <event name="wxEVT_AUINOTEBOOK_END_DRAG" class="wxAuiNotebookEvent" help="Dragging has ended."/>
    <event name="wxEVT_AUINOTEBOOK_DRAG_MOTION" class="wxAuiNotebookEvent" help="Emitted during a drag and drop operation."/>
    <event name="wxEVT_AUINOTEBOOK_ALLOW_DND" class="wxAuiNotebookEvent"
        help="Whether to allow a tab to be dropped. This event must be specially allowed."/>
    <event name="wxEVT_AUINOTEBOOK_DRAG_DONE" class="wxAuiNotebookEvent" help="Notify that the tab has been dragged."/>
    <event name="wxEVT_AUINOTEBOOK_TAB_MIDDLE_DOWN" class="wxAuiNotebookEvent" help="The middle mouse button is pressed on a tab."/>
    <event name="wxEVT_AUINOTEBOOK_TAB_MIDDLE_IP" class="wxAuiNotebookEvent" help="The middle mouse button is released on a tab."/>
    <event name="wxEVT_AUINOTEBOOK_TAB_RIGHT_DOWN" class="wxAuiNotebookEvent" help="The right mouse button is pressed on a tab."/>
    <event name="wxEVT_AUINOTEBOOK_TAB_RIGHT_UP" class="wxAuiNotebookEvent" help="The right mouse button is released on a tab."/>
    <event name="wxEVT_AUINOTEBOOK_BG_DCLICK" class="wxAuiNotebookEvent" help="Double clicked on the tabs background area."/>
  </gen>

  <gen class="auinotebookpage" image="auinotebook" type="auinotebookpage">
    <property name="label" type="string_escapes">a page</property>
    <property name="bitmap" type="image" help="Page Image"/>
    <property name="select" type="bool" help="Select Page when Adding">0</property>
  </gen>
-->

<gen class="wxAuiToolBar" image="auitoolbar" type="aui_toolbar">
    <inherits class="wxWindow"/>
    <inherits class="Window Events"/>
    <property name="var_name" type="string">m_auiToolBar</property>
    <property name="class_access" type="option">
        <option name="none"/>
        <option name="protected:"/>
        <option name="public:"/>
      protected:</property>
    <property name="bitmapsize" type="wxSize"
        help="Default size of each tool bitmap. The default bitmap size is 16 by 15 pixels."/>
    <property name="margins" type="wxSize"
        help="Values to be used as margins for the toolbar."/>
    <property name="packing" type="uint"
        help="Value used for spacing tools. The packing is used for spacing in the vertical direction if the toolbar is horizontal, and for spacing in the horizontal direction if the toolbar is vertical.">1</property>
    <property name="separation" type="uint"
        help="The default separator size. This is the size between each toolbar tool.">
      5</property>
    <property name="style" type="bitlist">
        <option name="wxAUI_TB_TEXT"
            help="Shows the text in the toolbar buttons; by default only icons are shown. "/>
        <option name="wxAUI_TB_NO_TOOLTIPS"
            help="Don't show tooltips on wxAuiToolBar items."/>
        <option name="wxAUI_TB_NO_AUTORESIZE"
            help="Do not auto-resize the wxAuiToolBar."/>
        <option name="wxAUI_TB_GRIPPER"
            help="Shows a gripper on the wxAuiToolBar."/>
        <option name="wxAUI_TB_OVERFLOW"
            help="The wxAuiToolBar can contain overflow items."/>
        <option name="wxAUI_TB_VERTICAL"
            help="Using this style forces the toolbar to be vertical and be only dockable to the left or right sides of the window whereas by default it can be horizontal or vertical and be docked anywhere."/>
        <option name="wxAUI_TB_HORZ_LAYOUT"
            help="Shows the text and the icons alongside, not vertically stacked. This style must be used with wxAUI_TB_TEXT"/>
        <option name="wxAUI_TB_HORIZONTAL"
            help="Analogous to wxAUI_TB_VERTICAL, but forces the toolbar to be horizontal, docking to the top or bottom of the window."/>
        <option name="wxAUI_TB_PLAIN_BACKGROUND"
            help="Draw a plain background (based on parent) instead of the default gradient background."/>
        <option name="wxAUI_TB_HORZ_TEXT"
            help="Shows the text alongside the icons, not vertically stacked."/>
        <option name="wxAUI_ORIENTATION_MASK "
            help="Shows the text in the toolbar buttons. By default only icons are shown."/>
        <option name="wxAUI_TB_DEFAULT_STYLE"
            help="By default only icons are shown."/>
        wxAUI_TB_DEFAULT_STYLE</property>
  </gen>

<gen class="auitool" image="tool" type="aui_tool">
    <property name="var_name" type="string">tool</property>
    <property name="class_access" type="option">
        <option name="none"/>
        <option name="protected:"/>
        <option name="public:"/>
      none</property>
    <property name="label" type="string_escapes"/>
    <property name="bitmap" type="image" help="The primary tool bitmap."/>
    <property name="kind" type="option">
        <option name="wxITEM_NORMAL"
            help="A normal toolbar button."/>
        <option name="wxITEM_CHECK"
            help="A checkable tool (stays pressed after it has been toggled)."/>
        <option name="wxITEM_DROPDOWN"
            help="Creates a normal tool button with a dropdown arrow next to it."/>
        <option name="wxITEM_RADIO"
        help="A checkable tool which makes part of a radio group of tools each of which is automatically unchecked whenever another button in the group is checked."/>
      wxITEM_NORMAL</property>
    <property name="context_menu" type="bool"
        help="Specifies that a drop-down menu button will appear next to the tool button. Used only with wxAuiToolBar.">0</property>
    <property name="tooltip" type="string_edit"
        help="Help string used in the tooltip."/>
    <property name="statusbar" type="string_edit"
        help="This string is shown in the statusbar (if any) of the parent frame when the mouse pointer is inside the tool."/>
    <property name="id" type="id">wxID_ANY</property>
    <event name="wxEVT_TOOL" class="wxCommandEvent"
        help="Same as wxEVT_MENU -- generated when the item is chosen in the toolbar or menu (if the same id was added to a menu)."/>
    <event name="wxEVT_UPDATE_UI" class="wxUpdateUIEvent" help=""/>
    <event name="wxEVT_AUITOOLBAR_TOOL_DROPDOWN" class="wxAuiToolBarEvent" help=""/>
    <event name="wxEVT_AUITOOLBAR_OVERFLOW_CLICK" class="wxAuiToolBarEvent" help=""/>
    <event name="wxEVT_AUITOOLBAR_RIGHT_CLICK" class="wxAuiToolBarEvent" help=""/>
    <event name="wxEVT_AUITOOLBAR_MIDDLE_CLICK" class="wxAuiToolBarEvent" help=""/>
    <event name="wxEVT_AUITOOLBAR_BEGIN_DRAG" class="wxAuiToolBarEvent" help=""/>
</gen>

</GeneratorDefitions>
